revibe/__init__.py
revibe/__main__.py
revibe/acp/__init__.py
revibe/acp/acp_agent.py
revibe/acp/entrypoint.py
revibe/acp/utils.py
revibe/acp/tools/__init__.py
revibe/acp/tools/base.py
revibe/acp/tools/session_update.py
revibe/acp/tools/builtins/bash.py
revibe/acp/tools/builtins/read_file.py
revibe/acp/tools/builtins/search_replace.py
revibe/acp/tools/builtins/todo.py
revibe/acp/tools/builtins/write_file.py
revibe/cli/__init__.py
revibe/cli/cli.py
revibe/cli/clipboard.py
revibe/cli/commands.py
revibe/cli/entrypoint.py
revibe/cli/history_manager.py
revibe/cli/terminal_setup.py
revibe/cli/autocompletion/__init__.py
revibe/cli/autocompletion/base.py
revibe/cli/autocompletion/path_completion.py
revibe/cli/autocompletion/slash_command.py
revibe/cli/textual_ui/__init__.py
revibe/cli/textual_ui/app.py
revibe/cli/textual_ui/terminal_theme.py
revibe/cli/textual_ui/handlers/__init__.py
revibe/cli/textual_ui/handlers/event_handler.py
revibe/cli/textual_ui/tcss/app/approval.tcss
revibe/cli/textual_ui/tcss/app/base.tcss
revibe/cli/textual_ui/tcss/app/bash.tcss
revibe/cli/textual_ui/tcss/app/bottom_bar.tcss
revibe/cli/textual_ui/tcss/app/config.tcss
revibe/cli/textual_ui/tcss/app/messages.tcss
revibe/cli/textual_ui/tcss/app/mode_indicator.tcss
revibe/cli/textual_ui/tcss/app/status.tcss
revibe/cli/textual_ui/tcss/app/todo_loading.tcss
revibe/cli/textual_ui/tcss/app/tool_results.tcss
revibe/cli/textual_ui/tcss/diff/base.tcss
revibe/cli/textual_ui/tcss/diff/header.tcss
revibe/cli/textual_ui/tcss/diff/hunk.tcss
revibe/cli/textual_ui/tcss/diff/lines.tcss
revibe/cli/textual_ui/tcss/diff/metadata.tcss
revibe/cli/textual_ui/tcss/diff/summary.tcss
revibe/cli/textual_ui/tcss/input/completion.tcss
revibe/cli/textual_ui/tcss/input/container.tcss
revibe/cli/textual_ui/tcss/input/focus.tcss
revibe/cli/textual_ui/tcss/input/hints.tcss
revibe/cli/textual_ui/tcss/input/input_area.tcss
revibe/cli/textual_ui/tcss/input/prompt.tcss
revibe/cli/textual_ui/tcss/selector/container.tcss
revibe-0.2.8.dist-info/METADATA
revibe-0.2.8.dist-info/WHEEL
revibe-0.2.8.dist-info/entry_points.txt
revibe-0.2.8.dist-info/licenses/LICENSE
revibe-0.2.8.dist-info/RECORD
