Metadata-Version: 2.4
Name: revibe
Version: 0.2.8
Summary: ReVibe - Multi-provider CLI coding agent
Project-URL: Homepage, https://github.com/OEvortex/revibe
Project-URL: Repository, https://github.com/OEvortex/revibe
Project-URL: Issues, https://github.com/OEvortex/revibe/issues
Project-URL: Documentation, https://github.com/OEvortex/revibe#readme
Author: OEvortex
License: Apache-2.0
License-File: LICENSE
Keywords: ai,cli,coding-assistant,developer-tools,groq,llm,mistral,multi-provider,openai
Classifier: Development Status :: 5 - Production/Stable
Classifier: Intended Audience :: Developers
Classifier: License :: OSI Approved :: Apache Software License
Classifier: Operating System :: OS Independent
Classifier: Programming Language :: Python
Classifier: Programming Language :: Python :: 3
Classifier: Programming Language :: Python :: 3.12
Classifier: Topic :: Software Development
Classifier: Topic :: Software Development :: Libraries :: Python Modules
Classifier: Topic :: Utilities
Requires-Python: >=3.12
Requires-Dist: agent-client-protocol==0.6.3
Requires-Dist: aiofiles>=24.1.0
Requires-Dist: httpx>=0.28.1
Requires-Dist: mcp>=1.14.0
Requires-Dist: mistralai==1.9.11
Requires-Dist: packaging>=24.1
Requires-Dist: pexpect>=4.9.0
Requires-Dist: pydantic-settings>=2.12.0
Requires-Dist: pydantic>=2.12.4
Requires-Dist: pyperclip>=1.11.0
Requires-Dist: python-dotenv>=1.0.0
Requires-Dist: pyyaml>=6.0.0
Requires-Dist: rich>=14.0.0
Requires-Dist: textual-speedups>=0.2.1
Requires-Dist: textual>=1.0.0
Requires-Dist: tomli-w>=1.2.0
Requires-Dist: watchfiles>=1.1.1
